psend/.gitignore
psend/__init__.py
psend/__main__.py
psend/functions.py
psend-0.1.9.dist-info/LICENSE
psend-0.1.9.dist-info/METADATA
psend-0.1.9.dist-info/WHEEL
psend-0.1.9.dist-info/entry_points.txt
psend-0.1.9.dist-info/RECORD
